utilities/__init__.py
utilities/__version__.py
utilities/helper.py
utilities/singleton.py
utilities/tinydb_exceptions.py
utilities/tinydb_wrapper.py
tl_utilities-3.0.4.dist-info/LICENSE
tl_utilities-3.0.4.dist-info/METADATA
tl_utilities-3.0.4.dist-info/WHEEL
tl_utilities-3.0.4.dist-info/top_level.txt
tl_utilities-3.0.4.dist-info/RECORD
