Metadata-Version: 2.1
Name: tl-utilities
Version: 3.0.4
Summary: Utility classes/methods used in VRM cloudless system
Home-page: https://github.com/thanhledev/utilities
Author: Thanh Le
Author-email: thanhledev@gmail.com
License: MIT
Platform: UNKNOWN
Classifier: License :: OSI Approved :: MIT License
Classifier: Programming Language :: Python
Classifier: Programming Language :: Python :: 3
Classifier: Programming Language :: Python :: 3.6
Requires-Python: >=3.6.0
Requires-Dist: tl-crmdtos (>=1.0.0)
Requires-Dist: tinydb
